Metadata-Version: 2.1
Name: plainquotes
Version: 0.0.1
Summary: This package adds functionality to the auto plain nested quotes in a string
Home-page: https://www.github.com/sersanchus/plainquotes
Author: Sergio Sancho Chust
Author-email: sersanchus@gmail.com
License: UNKNOWN
Platform: UNKNOWN
Classifier: Programming Language :: Python :: 3
Classifier: License :: OSI Approved :: MIT License
Classifier: Operating System :: OS Independent
License-File: LICENSE
